pypsdm/__init__.py
pypsdm/analysis/__init__.py
pypsdm/analysis/calc.py
pypsdm/analysis/grid.py
pypsdm/conversion/__init__.py
pypsdm/conversion/pandapower.py
pypsdm/db/__init__.py
pypsdm/db/gwr.py
pypsdm/db/utils.py
pypsdm/db/weather/__init__.py
pypsdm/db/weather/models.py
pypsdm/db/weather/proxy.py
pypsdm/db/weather/utils.py
pypsdm/errors.py
pypsdm/graph.py
pypsdm/io/__init__.py
pypsdm/io/utils.py
pypsdm/models/__init__.py
pypsdm/models/enums.py
pypsdm/models/gwr.py
pypsdm/models/input/__init__.py
pypsdm/models/input/connector/__init__.py
pypsdm/models/input/connector/connector.py
pypsdm/models/input/connector/lines.py
pypsdm/models/input/connector/switches.py
pypsdm/models/input/connector/transformer.py
pypsdm/models/input/container/__init__.py
pypsdm/models/input/container/grid.py
pypsdm/models/input/container/mixins.py
pypsdm/models/input/container/participants.py
pypsdm/models/input/container/raw_grid.py
pypsdm/models/input/create/__init__.py
pypsdm/models/input/create/grid_elements.py
pypsdm/models/input/create/participants.py
pypsdm/models/input/create/poi.py
pypsdm/models/input/create/thermal.py
pypsdm/models/input/create/utils.py
pypsdm/models/input/entity.py
pypsdm/models/input/mixins.py
pypsdm/models/input/node.py
pypsdm/models/input/participant/__init__.py
pypsdm/models/input/participant/bm.py
pypsdm/models/input/participant/charging.py
pypsdm/models/input/participant/em.py
pypsdm/models/input/participant/evcs.py
pypsdm/models/input/participant/evs.py
pypsdm/models/input/participant/fixed_feed_in.py
pypsdm/models/input/participant/hp.py
pypsdm/models/input/participant/load.py
pypsdm/models/input/participant/mixins.py
pypsdm/models/input/participant/participant.py
pypsdm/models/input/participant/pv.py
pypsdm/models/input/participant/storage.py
pypsdm/models/input/participant/wec.py
pypsdm/models/input/thermal/__init__.py
pypsdm/models/input/thermal/bus.py
pypsdm/models/input/thermal/grid.py
pypsdm/models/input/thermal/house.py
pypsdm-0.0.6.dist-info/LICENSE
pypsdm-0.0.6.dist-info/METADATA
pypsdm-0.0.6.dist-info/WHEEL
pypsdm-0.0.6.dist-info/RECORD
