Metadata-Version: 2.1
Name: pypsdm
Version: 0.0.6
Summary: 
Author: Thomas Oberliessen
Author-email: thomas.oberliessen@googlemail.com
Requires-Python: >3.11,<3.13
Classifier: Programming Language :: Python :: 3
Classifier: Programming Language :: Python :: 3.12
Requires-Dist: geoalchemy2 (>=0.17.1,<0.18.0)
Requires-Dist: loguru (>=0.7.2,<0.8.0)
Requires-Dist: matplotlib (>=3.10.1,<4.0.0)
Requires-Dist: networkx (>=3.1,<4.0)
Requires-Dist: numba (>=0.61.2,<0.62.0)
Requires-Dist: numpy (>=2.2.5,<3.0.0)
Requires-Dist: pandas (>=2.2.3,<2.3.0)
Requires-Dist: plotly (>=6.0.1,<7.0.0)
Requires-Dist: psycopg2 (>=2.9.10,<3.0.0)
Requires-Dist: pyhocon (>=0.3.60,<0.4.0)
Requires-Dist: python-dotenv (>=1.1.0,<2.0.0)
Requires-Dist: scipy (>=1.15.2,<2.0.0)
Requires-Dist: seaborn (==0.13.2)
Requires-Dist: shapely (>=2.0.7,<3.0.0)
Requires-Dist: sqlmodel (>=0.0.24,<0.0.25)
